MANIFEST.in
setup.py
django_zoneadmin.egg-info/PKG-INFO
django_zoneadmin.egg-info/SOURCES.txt
django_zoneadmin.egg-info/dependency_links.txt
django_zoneadmin.egg-info/pbr.json
django_zoneadmin.egg-info/requires.txt
django_zoneadmin.egg-info/top_level.txt
zone_admin/__init__.py
zone_admin/admin.py
zone_admin/apps.py
zone_admin/models.py
zone_admin/tests.py
zone_admin/views.py
zone_admin/widgets.py
zone_admin/static/admin/css/base.css
zone_admin/static/admin/css/custom-dashboard.css
zone_admin/static/admin/css/modeltranslation_fields.css
zone_admin/static/admin/js/custom_utils.js
zone_admin/static/admin/js/modeltranslation_fields.js
zone_admin/static/admin/vendor/jquery.min.js
zone_admin/static/admin/vendor/moment.js
zone_admin/static/admin/vendor/bootstrap/bootstrap-datetimepicker.min.css
zone_admin/static/admin/vendor/bootstrap/bootstrap-datetimepicker.min.js
zone_admin/static/admin/vendor/bootstrap/bootstrap-fileinput.min.css
zone_admin/static/admin/vendor/bootstrap/bootstrap-fileinput.min.js
zone_admin/static/admin/vendor/bootstrap/bootstrap-select.css
zone_admin/static/admin/vendor/bootstrap/bootstrap-select.js
zone_admin/static/admin/vendor/bootstrap/bootstrap-tagsinput.css
zone_admin/static/admin/vendor/bootstrap/bootstrap-tagsinput.js
zone_admin/static/admin/vendor/bootstrap/bootstrap.min.css
zone_admin/static/admin/vendor/bootstrap/bootstrap.min.js
zone_admin/static/admin/vendor/fonts/font-awesome.min.css
zone_admin/static/admin/vendor/fonts/fontawesome-webfont.ttf
zone_admin/static/admin/vendor/fonts/fontawesome-webfont.woff
zone_admin/static/admin/vendor/fonts/fontawesome-webfont.woff2
zone_admin/static/admin/vendor/fonts/glyphicons-halflings-regular.ttf
zone_admin/static/admin/vendor/fonts/glyphicons-halflings-regular.woff
zone_admin/static/admin/vendor/fonts/glyphicons-halflings-regular.woff2
zone_admin/static/admin/vendor/tinymce/license.txt
zone_admin/static/admin/vendor/tinymce/tinymce.min.js
zone_admin/static/admin/vendor/tinymce/langs/readme.md
zone_admin/static/admin/vendor/tinymce/plugins/advlist/plugin.min.js
zone_admin/static/admin/vendor/tinymce/plugins/anchor/plugin.min.js
zone_admin/static/admin/vendor/tinymce/plugins/autolink/plugin.min.js
