Metadata-Version: 1.0
Name: django-zoneadmin
Version: 0.3.5
Summary: Alternative django administration interface with bootstrap
Home-page: http://github.com/argaen/django_zoneadmin
Author: argaen
Author-email: manu.mirandad@gmail.com
License: UNKNOWN
Keywords: django,admin,bootstrap,djangozone
Platform: UNKNOWN
